blimp/__init__.py
blimp/bl_process.py
blimp/cli.py
blimp/main.py
blimp/misc.py
bl_imp-0.1.1.dist-info/LICENCE.md
bl_imp-0.1.1.dist-info/METADATA
bl_imp-0.1.1.dist-info/WHEEL
bl_imp-0.1.1.dist-info/entry_points.txt
bl_imp-0.1.1.dist-info/top_level.txt
bl_imp-0.1.1.dist-info/RECORD
