Metadata-Version: 2.1
Name: bl-imp
Version: 0.1.1
Summary: simple tool to download and update the JabberSpam blacklist list.
Home-page: https://github.com/mightyBroccoli/blacklist_importer
Author: Nico Wellpott
Author-email: nico@magicbroccoli.de
License: UNKNOWN
Platform: UNKNOWN
Classifier: Development Status :: 4 - Beta
Classifier: Intended Audience :: System Administrators
Classifier: License :: OSI Approved :: GNU General Public License v3 (GPLv3)
Classifier: Operating System :: Unix
Classifier: Programming Language :: Python :: 3
Classifier: Programming Language :: Python :: 3.7
Classifier: Programming Language :: Python :: 3.8
Classifier: Programming Language :: Python :: 3.9
Classifier: Programming Language :: Python :: Implementation :: CPython
Classifier: Topic :: Internet :: WWW/HTTP :: Dynamic Content
Requires-Python: >=3.7
License-File: LICENCE.md
Requires-Dist: appdirs (>=1.4)
Requires-Dist: requests (>=2.25)
Requires-Dist: ruamel.yaml (>=0.17)
Requires-Dist: ruamel.yaml.clib (>=0.2)
Requires-Dist: urllib3 (>=1.26)
